{
  "_class": "group",
  "booleanOperation": -1,
  "clippingMaskMode": 0,
  "do_objectID": "D248F4C6-F898-44EC-B47B-071B949731CB",
  "exportOptions": {
    "_class": "exportOptions",
    "do_objectID": "F3DD37BF-FE94-4D7F-B6D3-1D9A11E6F12A",
    "exportFormats": [
    ],
    "includedLayerIds": [
    ],
    "layerOptions": 0,
    "shouldTrim": false
  },
  "frame": {
    "_class": "rect",
    "constrainProportions": false,
    "do_objectID": "C8C53692-E7C5-4A9C-881B-A52052AE7D19",
    "height": 103,
    "width": 320,
    "x": 0,
    "y": 0
  },
  "groupLayout": {
    "_class": "MSImmutableFreeformGroupLayout",
    "do_objectID": "0737639F-8700-40FE-A02A-B9CC398CA61A"
  },
  "hasClickThrough": false,
  "hasClippingMask": false,
  "isFixedToViewport": false,
  "isFlippedHorizontal": false,
  "isFlippedVertical": false,
  "isLocked": false,
  "isVisible": true,
  "layerListExpandedType": 0,
  "layers": [
    {
      "class": "rectangle",
      "id": "3D9EAB27-F9CD-4A05-92FF-A2C9466016F7"
    },
    {
      "class": "group",
      "id": "3CAD8C5C-A778-4A73-996A-415DB9C3F9FF"
    }
  ],
  "name": "token",
  "nameIsFixed": true,
  "resizingConstraint": 63,
  "resizingType": 0,
  "rotation": 0,
  "shouldBreakMaskChain": false,
  "style": {
    "_class": "style",
    "blur": {
      "_class": "blur",
      "center": "{0.5, 0.5}",
      "do_objectID": "DE82107F-F06C-46AE-A141-D6474FD81EA6",
      "isEnabled": false,
      "motionAngle": 0,
      "radius": 7.999999523162842,
      "saturation": 1,
      "type": 0
    },
    "do_objectID": "528642DC-C8D1-4583-BEA0-89A90DACA184",
    "endMarkerType": 0,
    "fills": [
      {
        "_class": "fill",
        "color": {
          "_class": "color",
          "alpha": 1,
          "blue": 1,
          "green": 1,
          "red": 1
        },
        "fillType": 0,
        "isEnabled": true,
        "noiseIndex": 0,
        "noiseIntensity": 0,
        "patternFillType": 0,
        "patternTileScale": 1
      }
    ],
    "miterLimit": 10,
    "startMarkerType": 0,
    "windingRule": 1
  }
}