{
  "_class": "group",
  "booleanOperation": -1,
  "clippingMaskMode": 0,
  "do_objectID": "58381A60-E649-46D3-B549-4E35F19BA1C7",
  "exportOptions": {
    "_class": "exportOptions",
    "do_objectID": "E8E621A3-41DF-43D1-8C43-1F3E60C26252",
    "exportFormats": [
    ],
    "includedLayerIds": [
    ],
    "layerOptions": 0,
    "shouldTrim": false
  },
  "frame": {
    "_class": "rect",
    "constrainProportions": false,
    "do_objectID": "3C908BD9-B52E-4A8F-932F-D601314B1E52",
    "height": 500,
    "width": 314,
    "x": 294,
    "y": 0
  },
  "groupLayout": {
    "_class": "MSImmutableFreeformGroupLayout",
    "do_objectID": "2D7B7005-BAB6-4E74-AC09-842245EA0996"
  },
  "hasClickThrough": false,
  "hasClippingMask": false,
  "isFixedToViewport": false,
  "isFlippedHorizontal": false,
  "isFlippedVertical": false,
  "isLocked": false,
  "isVisible": true,
  "layerListExpandedType": 2,
  "layers": [
    {
      "class": "rectangle",
      "id": "4E31380C-E1E7-4D43-AABC-98BF55687491"
    },
    {
      "class": "bitmap",
      "id": "D883BFE5-72A7-4EEF-9476-EC97713870F4"
    }
  ],
  "name": "Bitmap Copy 11",
  "nameIsFixed": false,
  "resizingConstraint": 63,
  "resizingType": 0,
  "rotation": 0,
  "shouldBreakMaskChain": false,
  "style": {
    "_class": "style",
    "do_objectID": "7242CBEF-EAA2-4C7F-BA19-D5A2F831ED05",
    "endMarkerType": 0,
    "miterLimit": 10,
    "startMarkerType": 0,
    "windingRule": 1
  }
}