{
  "_class": "group",
  "booleanOperation": 0,
  "clippingMaskMode": 0,
  "do_objectID": "31674388-5FE6-4F8F-85F5-E82746D2058F",
  "exportOptions": {
    "_class": "exportOptions",
    "do_objectID": "455D4174-75A8-42E8-9704-01309778D546",
    "exportFormats": [
      {
        "_class": "exportFormat",
        "absoluteSize": 0,
        "fileFormat": "jpg",
        "name": "",
        "namingScheme": 0,
        "scale": 1,
        "visibleScaleType": 0
      }
    ],
    "includedLayerIds": [
    ],
    "layerOptions": 0,
    "shouldTrim": false
  },
  "frame": {
    "_class": "rect",
    "constrainProportions": true,
    "do_objectID": "447E21D7-89EC-4187-970F-5FF1F5E4A0A2",
    "height": 156,
    "width": 158,
    "x": 20,
    "y": 63
  },
  "groupLayout": {
    "_class": "MSImmutableFreeformGroupLayout",
    "do_objectID": "528F08C5-DFAF-42FC-97D8-0BC783BA5188"
  },
  "hasClickThrough": false,
  "hasClippingMask": false,
  "isFixedToViewport": false,
  "isFlippedHorizontal": false,
  "isFlippedVertical": false,
  "isLocked": false,
  "isVisible": true,
  "layerListExpandedType": 0,
  "layers": [
    {
      "class": "rectangle",
      "id": "76A3E7BC-9D00-4323-8D60-0682F408DA99"
    },
    {
      "class": "bitmap",
      "id": "B2959B18-8F2C-4DE6-A827-17B9E8BB0D76"
    }
  ],
  "name": "Bitmap",
  "nameIsFixed": false,
  "resizingConstraint": 63,
  "resizingType": 0,
  "rotation": 0,
  "shouldBreakMaskChain": false,
  "style": {
    "_class": "style",
    "do_objectID": "06C48E5D-4D1C-465B-9220-91A40A7FDEFA",
    "endMarkerType": 0,
    "miterLimit": 10,
    "startMarkerType": 0,
    "windingRule": 1
  }
}