{
  "_class": "symbolInstance",
  "booleanOperation": -1,
  "clippingMaskMode": 0,
  "do_objectID": "44DD30C6-7FA5-40A5-B738-C345B9E0A99E",
  "exportOptions": {
    "_class": "exportOptions",
    "do_objectID": "95978DEA-21EC-468A-8F5F-5133AB99C6B7",
    "exportFormats": [
    ],
    "includedLayerIds": [
    ],
    "layerOptions": 0,
    "shouldTrim": false
  },
  "frame": {
    "_class": "rect",
    "constrainProportions": false,
    "do_objectID": "D66AD45B-8B15-4B43-A6BB-B9C1E2A53F21",
    "height": 24,
    "width": 1024,
    "x": 0,
    "y": 187
  },
  "hasClippingMask": false,
  "horizontalSpacing": 0,
  "isFixedToViewport": false,
  "isFlippedHorizontal": false,
  "isFlippedVertical": false,
  "isLocked": false,
  "isVisible": true,
  "layerListExpandedType": 0,
  "name": "row 3",
  "nameIsFixed": true,
  "overrideValues": [
  ],
  "resizingConstraint": 63,
  "resizingType": 0,
  "rotation": 0,
  "scale": 1,
  "shouldBreakMaskChain": false,
  "style": {
    "_class": "style",
    "do_objectID": "63423A19-166A-400C-A829-8A8E571F0CE1",
    "endMarkerType": 0,
    "miterLimit": 10,
    "startMarkerType": 0,
    "windingRule": 1
  },
  "symbolID": "2796DB5F-7A2E-4078-B497-A8B80DE0D1B9",
  "verticalSpacing": 0
}