{
  "_class": "symbolInstance",
  "booleanOperation": -1,
  "clippingMaskMode": 0,
  "do_objectID": "71208903-6B53-475A-9B47-9C040694E921",
  "exportOptions": {
    "_class": "exportOptions",
    "do_objectID": "59BC8201-0C31-4802-91D0-C8964359ABC5",
    "exportFormats": [
    ],
    "includedLayerIds": [
    ],
    "layerOptions": 0,
    "shouldTrim": false
  },
  "frame": {
    "_class": "rect",
    "constrainProportions": false,
    "do_objectID": "628F5015-BE2A-4558-8E53-F22663DA9649",
    "height": 67,
    "width": 112,
    "x": 381,
    "y": 0
  },
  "hasClippingMask": false,
  "horizontalSpacing": 0,
  "isFixedToViewport": false,
  "isFlippedHorizontal": false,
  "isFlippedVertical": false,
  "isLocked": false,
  "isVisible": true,
  "layerListExpandedType": 0,
  "name": "a-checkout/inactive/shipping",
  "nameIsFixed": false,
  "overrideValues": [
  ],
  "resizingConstraint": 63,
  "resizingType": 0,
  "rotation": 0,
  "scale": 1,
  "shouldBreakMaskChain": false,
  "style": {
    "_class": "style",
    "do_objectID": "0626CA57-6ADB-46FF-879F-85139E89C8C5",
    "endMarkerType": 0,
    "miterLimit": 10,
    "startMarkerType": 0,
    "windingRule": 1
  },
  "symbolID": "B21AD98F-B799-4966-9FC5-992A1F0BC276",
  "verticalSpacing": 0
}