{
  "_class": "group",
  "booleanOperation": 0,
  "clippingMaskMode": 0,
  "do_objectID": "DE8B42F1-2B10-4FA3-9D4F-E8617C63FAE4",
  "exportOptions": {
    "_class": "exportOptions",
    "do_objectID": "2F747659-F216-4C24-A9F5-52F91438AB84",
    "exportFormats": [
    ],
    "includedLayerIds": [
    ],
    "layerOptions": 0,
    "shouldTrim": false
  },
  "frame": {
    "_class": "rect",
    "constrainProportions": false,
    "do_objectID": "EA14FBD5-672E-48B7-AED7-AA8A5EB00E13",
    "height": 10,
    "width": 24,
    "x": 246,
    "y": 31
  },
  "groupLayout": {
    "_class": "MSImmutableFreeformGroupLayout",
    "do_objectID": "38CF4F63-61B8-4F9C-9756-8361BF451B32"
  },
  "hasClickThrough": false,
  "hasClippingMask": false,
  "isFixedToViewport": false,
  "isFlippedHorizontal": false,
  "isFlippedVertical": false,
  "isLocked": false,
  "isVisible": true,
  "layerListExpandedType": 2,
  "layers": [
    {
      "class": "shapePath",
      "id": "4B3DFD81-056E-4F5A-9B5F-552DDD2607E3"
    }
  ],
  "name": "Group",
  "nameIsFixed": false,
  "resizingConstraint": 63,
  "resizingType": 0,
  "rotation": -360,
  "shouldBreakMaskChain": false,
  "style": {
    "_class": "style",
    "do_objectID": "C3317B3F-DCAA-48D4-BC70-6D914FE7BDC4",
    "endMarkerType": 0,
    "fills": [
      {
        "_class": "fill",
        "color": {
          "_class": "color",
          "alpha": 1,
          "blue": 0,
          "green": 0,
          "red": 0
        },
        "fillType": 0,
        "isEnabled": true,
        "noiseIndex": 0,
        "noiseIntensity": 0,
        "patternFillType": 1,
        "patternTileScale": 1
      }
    ],
    "miterLimit": 10,
    "startMarkerType": 0,
    "windingRule": 1
  }
}