{
  "_class": "bitmap",
  "booleanOperation": 0,
  "clippingMask": "{{0, 0}, {1, 1}}",
  "clippingMaskMode": 0,
  "do_objectID": "1A62604A-6BD8-479C-8257-A920C9127546",
  "exportOptions": {
    "_class": "exportOptions",
    "do_objectID": "C436CBE0-74B8-46F3-BD87-171E6DB41550",
    "exportFormats": [
    ],
    "includedLayerIds": [
    ],
    "layerOptions": 0,
    "shouldTrim": false
  },
  "fillReplacesImage": false,
  "frame": {
    "_class": "rect",
    "constrainProportions": true,
    "do_objectID": "EE14BFDF-B957-4420-A7E6-A267D6CEA56C",
    "height": 349,
    "width": 249,
    "x": 0,
    "y": -39
  },
  "hasClippingMask": false,
  "image": {
    "_class": "MSJSONFileReference",
    "_ref": "images/74379e65cd655a5bc1e5d9afdcd7f27a44babd5f.png",
    "_ref_class": "MSImageData"
  },
  "intendedDPI": 0,
  "isFixedToViewport": false,
  "isFlippedHorizontal": false,
  "isFlippedVertical": false,
  "isLocked": false,
  "isVisible": true,
  "layerListExpandedType": 0,
  "name": "Bitmap",
  "nameIsFixed": false,
  "resizingConstraint": 63,
  "resizingType": 0,
  "rotation": 0,
  "shouldBreakMaskChain": false,
  "style": {
    "_class": "style",
    "do_objectID": "46FA2F3F-7773-4186-ACE7-C3A0F7C56F67",
    "endMarkerType": 0,
    "miterLimit": 10,
    "startMarkerType": 0,
    "windingRule": 1
  }
}