{
  "_class": "group",
  "booleanOperation": 0,
  "clippingMaskMode": 0,
  "do_objectID": "858BCC2E-15BD-4293-8347-1C8C00C5E0C6",
  "exportOptions": {
    "_class": "exportOptions",
    "do_objectID": "CF0A33A0-CFD7-4146-B951-A88C418344D4",
    "exportFormats": [
    ],
    "includedLayerIds": [
    ],
    "layerOptions": 0,
    "shouldTrim": false
  },
  "frame": {
    "_class": "rect",
    "constrainProportions": false,
    "do_objectID": "67F192DB-8F97-4E51-9B2B-6DA0CCE59488",
    "height": 48,
    "width": 335,
    "x": 19,
    "y": 438
  },
  "groupLayout": {
    "_class": "MSImmutableFreeformGroupLayout",
    "do_objectID": "D3E63E65-5897-488C-A301-3F5B6B2BBD7E"
  },
  "hasClickThrough": false,
  "hasClippingMask": false,
  "isFixedToViewport": false,
  "isFlippedHorizontal": false,
  "isFlippedVertical": false,
  "isLocked": false,
  "isVisible": true,
  "layerListExpandedType": 0,
  "layers": [
    {
      "class": "shapePath",
      "id": "98BE99B9-A587-4921-952E-D9A1B5E38E5D"
    },
    {
      "class": "text",
      "id": "11344816-7ED3-45EA-904C-B31A01F29996"
    },
    {
      "class": "text",
      "id": "D4C41AC0-E767-49D6-ABA5-07947E7360F6"
    }
  ],
  "name": "Group 2",
  "nameIsFixed": false,
  "resizingConstraint": 63,
  "resizingType": 0,
  "rotation": 0,
  "shouldBreakMaskChain": false,
  "style": {
    "_class": "style",
    "do_objectID": "5BBA5EA1-3215-4E63-9221-A549D5569501",
    "endMarkerType": 0,
    "miterLimit": 10,
    "startMarkerType": 0,
    "windingRule": 1
  }
}