{
  "_class": "group",
  "booleanOperation": 0,
  "clippingMaskMode": 0,
  "do_objectID": "A7277F6A-3F78-4B16-A35D-9C150202ED98",
  "exportOptions": {
    "_class": "exportOptions",
    "do_objectID": "C8E9BD22-E0C9-4FDD-9861-8389DABCFB06",
    "exportFormats": [
    ],
    "includedLayerIds": [
    ],
    "layerOptions": 0,
    "shouldTrim": false
  },
  "frame": {
    "_class": "rect",
    "constrainProportions": false,
    "do_objectID": "4071C18A-9803-49FE-A882-78D2789E268C",
    "height": 264,
    "width": 446,
    "x": 0,
    "y": 1595
  },
  "groupLayout": {
    "_class": "MSImmutableFreeformGroupLayout",
    "do_objectID": "C1BAFBBB-24C8-4DCD-8CF9-1C8DC22A344E"
  },
  "hasClickThrough": false,
  "hasClippingMask": false,
  "isFixedToViewport": false,
  "isFlippedHorizontal": false,
  "isFlippedVertical": false,
  "isLocked": false,
  "isVisible": true,
  "layerListExpandedType": 0,
  "layers": [
    {
      "class": "group",
      "id": "65D22015-ADF5-4F1D-9383-6112D33B8E74"
    },
    {
      "class": "group",
      "id": "D26271C1-05A3-49B6-A249-41E2C24F2155"
    },
    {
      "class": "group",
      "id": "831BFCB1-C926-4C2E-BEDA-645F042915A4"
    },
    {
      "class": "text",
      "id": "8FC84CF3-0CBE-45AE-B5A0-9CE69D023CEC"
    },
    {
      "class": "text",
      "id": "43E62730-7E90-4DBC-9770-386747ECED56"
    },
    {
      "class": "text",
      "id": "53BC698B-5E2E-4B89-A053-7E27C212E71D"
    },
    {
      "class": "text",
      "id": "83A98BC9-DCBA-4E41-96A2-E7F79485D2CB"
    },
    {
      "class": "text",
      "id": "1D276348-E14B-43AF-A2DC-7B8674E9D394"
    }
  ],
  "name": "Group 6",
  "nameIsFixed": false,
  "resizingConstraint": 63,
  "resizingType": 0,
  "rotation": 0,
  "shouldBreakMaskChain": false,
  "style": {
    "_class": "style",
    "do_objectID": "DD688734-2C66-4D19-993D-B929A63E8D9B",
    "endMarkerType": 0,
    "miterLimit": 10,
    "startMarkerType": 0,
    "windingRule": 1
  }
}