{
  "_class": "shapePath",
  "booleanOperation": -1,
  "clippingMaskMode": 0,
  "do_objectID": "91A0F8E4-E332-4768-ABA6-BBCDA2D8D2C0",
  "edited": true,
  "exportOptions": {
    "_class": "exportOptions",
    "do_objectID": "9482F71E-7ED4-487B-B186-2DF7A981299C",
    "exportFormats": [
    ],
    "includedLayerIds": [
    ],
    "layerOptions": 0,
    "shouldTrim": false
  },
  "frame": {
    "_class": "rect",
    "constrainProportions": false,
    "do_objectID": "9958B4F5-C7B4-4023-8200-310A6BE69764",
    "height": 0.1058906030855518,
    "width": 0.1059863482545538,
    "x": 34.85857471455917,
    "y": 11.85346392116411
  },
  "hasClippingMask": false,
  "isClosed": true,
  "isFixedToViewport": false,
  "isFlippedHorizontal": false,
  "isFlippedVertical": false,
  "isLocked": false,
  "isVisible": true,
  "layerListExpandedType": 0,
  "name": "Path",
  "nameIsFixed": false,
  "pointRadiusBehaviour": 0,
  "points": [
    {
      "_class": "curvePoint",
      "cornerRadius": 0,
      "curveFrom": "{0.94170129870144592, 0.24723969464255902}",
      "curveMode": 4,
      "curveTo": "{0.36270129870143819, -0.10476030535741643}",
      "hasCurveFrom": true,
      "hasCurveTo": true,
      "point": "{0.56470129870143637, 0.01523969464258812}"
    },
    {
      "_class": "curvePoint",
      "cornerRadius": 0,
      "curveFrom": "{-0.25629870129853316, 0.51623969464256447}",
      "curveMode": 3,
      "curveTo": "{0.32070129870146502, 0.86923969464257311}",
      "hasCurveFrom": true,
      "hasCurveTo": true,
      "point": "{0.11770129870143364, 0.74623969464258266}"
    }
  ],
  "resizingConstraint": 63,
  "resizingType": 0,
  "rotation": 0,
  "shouldBreakMaskChain": false,
  "style": {
    "_class": "style",
    "do_objectID": "719E8A1D-9AF2-413E-8F08-840C1EFEB8DC",
    "endMarkerType": 0,
    "fills": [
      {
        "_class": "fill",
        "color": {
          "_class": "color",
          "alpha": 1,
          "blue": 0.1764705882352941,
          "green": 0.1764705882352941,
          "red": 0.1764705882352941
        },
        "fillType": 0,
        "isEnabled": true,
        "noiseIndex": 0,
        "noiseIntensity": 0,
        "patternFillType": 1,
        "patternTileScale": 1
      }
    ],
    "miterLimit": 10,
    "startMarkerType": 0,
    "windingRule": 1
  }
}