{
  "_class": "symbolMaster",
  "allowsOverrides": true,
  "backgroundColor": {
    "_class": "color",
    "alpha": 1,
    "blue": 1,
    "green": 1,
    "red": 1
  },
  "booleanOperation": -1,
  "changeIdentifier": 909,
  "clippingMaskMode": 0,
  "do_objectID": "31397172-898E-480D-BCD3-B105FF0BA587",
  "exportOptions": {
    "_class": "exportOptions",
    "exportFormats": [
    ],
    "includedLayerIds": [
    ],
    "layerOptions": 0,
    "shouldTrim": false
  },
  "frame": {
    "_class": "rect",
    "constrainProportions": false,
    "height": 242,
    "width": 512,
    "x": 70156,
    "y": 272
  },
  "groupLayout": {
    "_class": "MSImmutableFreeformGroupLayout"
  },
  "hasBackgroundColor": false,
  "hasClickThrough": true,
  "hasClippingMask": false,
  "horizontalRulerData": {
    "_class": "rulerData",
    "base": 0,
    "guides": [
    ]
  },
  "includeBackgroundColorInExport": true,
  "includeBackgroundColorInInstance": false,
  "includeInCloudUpload": true,
  "isFixedToViewport": false,
  "isFlippedHorizontal": false,
  "isFlippedVertical": false,
  "isFlowHome": false,
  "isLocked": false,
  "isVisible": true,
  "layerListExpandedType": 2,
  "layers": [
    {
      "class": "rectangle",
      "id": "3B571093-8909-4935-A8DD-BB47BF5FE2B6"
    },
    {
      "class": "symbolInstance",
      "id": "9BAD890A-FE54-4849-A21B-B3D89F88F5B3"
    },
    {
      "class": "symbolInstance",
      "id": "A217A3C5-B9B7-44C5-9757-BEE442D93DDA"
    },
    {
      "class": "symbolInstance",
      "id": "68ABBAE8-747D-42E3-A8EF-B750713B7326"
    },
    {
      "class": "text",
      "id": "890484B9-D0E2-443A-8BB8-F86E1F5F8BB2"
    },
    {
      "class": "text",
      "id": "2DCB5F5B-2443-430B-A415-5D7F6F0E960A"
    },
    {
      "class": "text",
      "id": "4DB653A7-9C7B-4C6B-9C58-A921E57021DC"
    },
    {
      "class": "symbolInstance",
      "id": "2DF243BD-4612-40DF-BD1D-765B10A2E405"
    }
  ],
  "name": "modal / group / 03 danger / 02 label",
  "nameIsFixed": true,
  "overrideProperties": [
    {
      "_class": "MSImmutableOverrideProperty",
      "canOverride": false,
      "overrideName": "2DF243BD-4612-40DF-BD1D-765B10A2E405/8E4FAAE6-F0AF-4BAA-B2D1-78C5288BB957_layerStyle"
    },
    {
      "_class": "MSImmutableOverrideProperty",
      "canOverride": true,
      "overrideName": "A217A3C5-B9B7-44C5-9757-BEE442D93DDA_symbolID"
    },
    {
      "_class": "MSImmutableOverrideProperty",
      "canOverride": true,
      "overrideName": "68ABBAE8-747D-42E3-A8EF-B750713B7326_symbolID"
    },
    {
      "_class": "MSImmutableOverrideProperty",
      "canOverride": true,
      "overrideName": "9BAD890A-FE54-4849-A21B-B3D89F88F5B3_symbolID"
    },
    {
      "_class": "MSImmutableOverrideProperty",
      "canOverride": false,
      "overrideName": "2DF243BD-4612-40DF-BD1D-765B10A2E405_symbolID"
    },
    {
      "_class": "MSImmutableOverrideProperty",
      "canOverride": false,
      "overrideName": "4DB653A7-9C7B-4C6B-9C58-A921E57021DC_textStyle"
    },
    {
      "_class": "MSImmutableOverrideProperty",
      "canOverride": false,
      "overrideName": "3B571093-8909-4935-A8DD-BB47BF5FE2B6_layerStyle"
    },
    {
      "_class": "MSImmutableOverrideProperty",
      "canOverride": true,
      "overrideName": "4DB653A7-9C7B-4C6B-9C58-A921E57021DC_stringValue"
    },
    {
      "_class": "MSImmutableOverrideProperty",
      "canOverride": false,
      "overrideName": "2DCB5F5B-2443-430B-A415-5D7F6F0E960A_textStyle"
    },
    {
      "_class": "MSImmutableOverrideProperty",
      "canOverride": true,
      "overrideName": "2DCB5F5B-2443-430B-A415-5D7F6F0E960A_stringValue"
    },
    {
      "_class": "MSImmutableOverrideProperty",
      "canOverride": true,
      "overrideName": "890484B9-D0E2-443A-8BB8-F86E1F5F8BB2_stringValue"
    },
    {
      "_class": "MSImmutableOverrideProperty",
      "canOverride": false,
      "overrideName": "890484B9-D0E2-443A-8BB8-F86E1F5F8BB2_textStyle"
    }
  ],
  "resizesContent": true,
  "resizingConstraint": 63,
  "resizingType": 0,
  "rotation": 0,
  "shouldBreakMaskChain": true,
  "style": {
    "_class": "style",
    "endMarkerType": 0,
    "miterLimit": 10,
    "startMarkerType": 0,
    "windingRule": 1
  },
  "symbolID": "696E8BF2-ED34-47BC-BFD1-F1923AF04376",
  "verticalRulerData": {
    "_class": "rulerData",
    "base": 0,
    "guides": [
    ]
  }
}