{
  "_class": "rectangle",
  "booleanOperation": -1,
  "clippingMaskMode": 0,
  "do_objectID": "937EE22E-8AA9-4B7F-9D87-388AEE4F8DFB",
  "edited": true,
  "exportOptions": {
    "_class": "exportOptions",
    "do_objectID": "1E1F1828-45F9-46EA-A9FB-AB352F60E1A7",
    "exportFormats": [
    ],
    "includedLayerIds": [
    ],
    "layerOptions": 0,
    "shouldTrim": false
  },
  "fixedRadius": 4,
  "frame": {
    "_class": "rect",
    "constrainProportions": false,
    "do_objectID": "D3010482-5448-46A6-BFD5-FCCCE407F560",
    "height": 253,
    "width": 328,
    "x": 0,
    "y": 0
  },
  "hasClippingMask": false,
  "hasConvertedToNewRoundCorners": true,
  "isClosed": true,
  "isFixedToViewport": false,
  "isFlippedHorizontal": false,
  "isFlippedVertical": false,
  "isLocked": false,
  "isVisible": true,
  "layerListExpandedType": 0,
  "name": "Bg",
  "nameIsFixed": true,
  "pointRadiusBehaviour": 1,
  "points": [
    {
      "_class": "curvePoint",
      "cornerRadius": 4,
      "curveFrom": "{0, 1.7772868815763357e-17}",
      "curveMode": 1,
      "curveTo": "{0, 1.7772868815763357e-17}",
      "hasCurveFrom": false,
      "hasCurveTo": false,
      "point": "{0, 1.7772868815763357e-17}"
    },
    {
      "_class": "curvePoint",
      "cornerRadius": 4,
      "curveFrom": "{1, -9.4160841097997924e-17}",
      "curveMode": 1,
      "curveTo": "{1, -9.4160841097997924e-17}",
      "hasCurveFrom": false,
      "hasCurveTo": false,
      "point": "{1, -9.4160841097997924e-17}"
    },
    {
      "_class": "curvePoint",
      "cornerRadius": 4,
      "curveFrom": "{1, 0.99999999999999867}",
      "curveMode": 1,
      "curveTo": "{1, 0.99999999999999867}",
      "hasCurveFrom": false,
      "hasCurveTo": false,
      "point": "{1, 0.99999999999999867}"
    },
    {
      "_class": "curvePoint",
      "cornerRadius": 4,
      "curveFrom": "{0, 0.99999999999999867}",
      "curveMode": 1,
      "curveTo": "{0, 0.99999999999999867}",
      "hasCurveFrom": false,
      "hasCurveTo": false,
      "point": "{0, 0.99999999999999867}"
    }
  ],
  "resizingConstraint": 63,
  "resizingType": 0,
  "rotation": 0,
  "shouldBreakMaskChain": false,
  "style": {
    "_class": "style",
    "borders": [
      {
        "_class": "border",
        "color": {
          "_class": "color",
          "alpha": 1,
          "blue": 1,
          "green": 1,
          "red": 1
        },
        "fillType": 0,
        "isEnabled": false,
        "position": 1,
        "thickness": 1
      }
    ],
    "do_objectID": "B819D005-E453-4774-B090-9B1B9B2116BC",
    "endMarkerType": 0,
    "fills": [
      {
        "_class": "fill",
        "color": {
          "_class": "color",
          "alpha": 1,
          "blue": 1,
          "green": 1,
          "red": 1
        },
        "fillType": 0,
        "gradient": {
          "_class": "gradient",
          "elipseLength": 0,
          "from": "{1, 0.047189295977011492}",
          "gradientType": 0,
          "stops": [
            {
              "_class": "gradientStop",
              "color": {
                "_class": "color",
                "alpha": 0.9,
                "blue": 0.4352941176470591,
                "green": 0.3803921568627451,
                "red": 1
              },
              "position": 0
            },
            {
              "_class": "gradientStop",
              "color": {
                "_class": "color",
                "alpha": 1,
                "blue": 0.2666666666666664,
                "green": 0.09019607843137256,
                "red": 1
              },
              "position": 1
            }
          ],
          "to": "{0, 1}"
        },
        "isEnabled": true,
        "noiseIndex": 0,
        "noiseIntensity": 0,
        "patternFillType": 1,
        "patternTileScale": 1
      }
    ],
    "miterLimit": 10,
    "shadows": [
      {
        "_class": "shadow",
        "blurRadius": 4,
        "color": {
          "_class": "color",
          "alpha": 0.2018229166666667,
          "blue": 0,
          "green": 0,
          "red": 0
        },
        "contextSettings": {
          "_class": "graphicsContextSettings",
          "blendMode": 0,
          "opacity": 1
        },
        "isEnabled": false,
        "offsetX": 0,
        "offsetY": 2,
        "spread": 0
      }
    ],
    "startMarkerType": 0,
    "windingRule": 1
  }
}