{
  "_class": "artboard",
  "backgroundColor": {
    "_class": "color",
    "alpha": 1,
    "blue": 1,
    "green": 1,
    "red": 1
  },
  "booleanOperation": -1,
  "clippingMaskMode": 0,
  "do_objectID": "42110D3D-3547-49B3-A60B-8219037519F9",
  "exportOptions": {
    "_class": "exportOptions",
    "exportFormats": [
    ],
    "includedLayerIds": [
    ],
    "layerOptions": 0,
    "shouldTrim": false
  },
  "frame": {
    "_class": "rect",
    "constrainProportions": false,
    "height": 1469,
    "width": 375,
    "x": 3064,
    "y": 6830
  },
  "groupLayout": {
    "_class": "MSImmutableFreeformGroupLayout"
  },
  "hasBackgroundColor": false,
  "hasClickThrough": true,
  "hasClippingMask": false,
  "horizontalRulerData": {
    "_class": "rulerData",
    "base": 0,
    "guides": [
    ]
  },
  "includeBackgroundColorInExport": true,
  "includeInCloudUpload": true,
  "isFixedToViewport": false,
  "isFlippedHorizontal": false,
  "isFlippedVertical": false,
  "isFlowHome": false,
  "isLocked": false,
  "isVisible": true,
  "layerListExpandedType": 2,
  "layers": [
    {
      "class": "group",
      "id": "9622558E-6254-4762-93CA-8A67BAED3810"
    },
    {
      "class": "group",
      "id": "75347892-1C56-4CD7-A4DE-3037DE7A0F4D"
    },
    {
      "class": "group",
      "id": "0297298D-1BA1-4A39-9907-F0AC4EB1503C"
    },
    {
      "class": "group",
      "id": "DA7B7B11-BFF9-4C0B-9AEE-5898EB8D34E5"
    },
    {
      "class": "group",
      "id": "06269666-78C2-442B-9586-B47ACAD8833F"
    },
    {
      "class": "group",
      "id": "59F69D61-DD4B-45AE-8427-3225D9ACB7B5"
    },
    {
      "class": "shapePath",
      "id": "2212051C-53E5-4CA6-A5DF-D83C7B3A1903"
    },
    {
      "class": "group",
      "id": "8AA446BC-ED3A-42BC-AEB6-AE2F970349EE"
    },
    {
      "class": "group",
      "id": "E8262959-972D-4CD6-8ECD-2F2CFFDE38CC"
    },
    {
      "class": "group",
      "id": "A9DE722B-B954-4278-9E8D-BF8EA660A597"
    },
    {
      "class": "group",
      "id": "29410954-9A0E-4EBF-BFFB-FD0B526973C3"
    },
    {
      "class": "symbolInstance",
      "id": "1A683F29-A5DB-4097-A28B-CAEFAF9FF65E"
    },
    {
      "class": "symbolInstance",
      "id": "14B587A4-7FDD-470D-85EE-3C23740F3069"
    },
    {
      "class": "group",
      "id": "454D849F-C7F7-411D-8CB5-74A044155F8D"
    },
    {
      "class": "rectangle",
      "id": "FDA3368C-73C7-4BCF-9BBB-D0F757DE4DBD"
    },
    {
      "class": "rectangle",
      "id": "9B0806AE-7C4D-4873-9B23-FDDCA717CD1E"
    },
    {
      "class": "rectangle",
      "id": "A009AC3F-8F7A-480C-BA19-5E9170770AEF"
    },
    {
      "class": "rectangle",
      "id": "62C7EBB8-E719-40B6-ABAB-8C3D70BA9F9E"
    },
    {
      "class": "rectangle",
      "id": "BFD00FC5-E83B-4B47-BE3B-B6249B0E9085"
    },
    {
      "class": "rectangle",
      "id": "550D43C6-C015-4251-82F1-13388E137683"
    },
    {
      "class": "rectangle",
      "id": "1B8A5D91-D288-4614-A164-5C45463252BC"
    },
    {
      "class": "rectangle",
      "id": "250896E0-6E17-46A2-BFBA-300C15221614"
    },
    {
      "class": "rectangle",
      "id": "A2EB13E8-A8C1-4CB7-B395-554C9F9F0B0B"
    },
    {
      "class": "rectangle",
      "id": "B018EF66-8EFB-4190-869B-DD765DA5716C"
    },
    {
      "class": "rectangle",
      "id": "4D728F22-2B87-4934-8279-DFC5C52F1DA0"
    },
    {
      "class": "rectangle",
      "id": "6CD31315-8C8F-4A44-8A17-9E6FC3D2D608"
    },
    {
      "class": "rectangle",
      "id": "A068376F-6C07-465C-88BC-4F799A6E4FF5"
    },
    {
      "class": "rectangle",
      "id": "F6BFF5EB-B8DB-44AF-BE64-5C62B45D565A"
    },
    {
      "class": "rectangle",
      "id": "C6750138-A37B-49FC-B4DA-3A44B48BC820"
    },
    {
      "class": "rectangle",
      "id": "E2FED6CF-9B41-445B-8B7A-75117C65C377"
    },
    {
      "class": "rectangle",
      "id": "ABD5A575-4E70-4D84-A2D5-FA53445C422D"
    },
    {
      "class": "rectangle",
      "id": "B2AAD28B-C46A-47D2-9778-C0C2FDC1751C"
    }
  ],
  "layout": {
    "_class": "layoutGrid",
    "columnWidth": 48,
    "drawHorizontal": true,
    "drawHorizontalLines": false,
    "drawVertical": true,
    "gutterHeight": 4,
    "gutterWidth": 9,
    "guttersOutside": false,
    "horizontalOffset": 21,
    "isEnabled": false,
    "numberOfColumns": 6,
    "rowHeightMultiplication": 1,
    "totalWidth": 333
  },
  "maintainScrollPosition": false,
  "name": "PLP Skeleton",
  "nameIsFixed": true,
  "presetDictionary": {
    "allowResizedMatching": 1,
    "height": 667,
    "name": "iPhone 8",
    "offersLandscapeVariant": 1,
    "width": 375
  },
  "resizesContent": false,
  "resizingConstraint": 63,
  "resizingType": 0,
  "rotation": 0,
  "shouldBreakMaskChain": true,
  "style": {
    "_class": "style",
    "blur": {
      "_class": "blur",
      "center": "{0.5, 0.5}",
      "isEnabled": false,
      "motionAngle": 0,
      "radius": 10,
      "saturation": 1,
      "type": 0
    },
    "borderOptions": {
      "_class": "borderOptions",
      "dashPattern": [
      ],
      "isEnabled": true,
      "lineCapStyle": 0,
      "lineJoinStyle": 0
    },
    "borders": [
    ],
    "colorControls": {
      "_class": "colorControls",
      "brightness": 0,
      "contrast": 1,
      "hue": 0,
      "isEnabled": false,
      "saturation": 1
    },
    "contextSettings": {
      "_class": "graphicsContextSettings",
      "blendMode": 0,
      "opacity": 1
    },
    "do_objectID": "9F79FE0B-4C22-4601-A4AE-4C34949D059D",
    "endMarkerType": 0,
    "fills": [
    ],
    "innerShadows": [
    ],
    "miterLimit": 10,
    "shadows": [
    ],
    "startMarkerType": 0,
    "windingRule": 1
  },
  "verticalRulerData": {
    "_class": "rulerData",
    "base": 0,
    "guides": [
    ]
  }
}