{
  "_class": "group",
  "booleanOperation": -1,
  "clippingMaskMode": 0,
  "do_objectID": "F22DC985-C296-43DA-B202-9C5F4A0BC3F8",
  "exportOptions": {
    "_class": "exportOptions",
    "do_objectID": "7F1BD60A-5244-48A7-A940-9551F4E87050",
    "exportFormats": [
    ],
    "includedLayerIds": [
    ],
    "layerOptions": 0,
    "shouldTrim": false
  },
  "frame": {
    "_class": "rect",
    "constrainProportions": false,
    "do_objectID": "F1A05B76-59BA-4A25-B663-7AC2C9C5C7FD",
    "height": 412,
    "width": 375,
    "x": 0,
    "y": 64
  },
  "groupLayout": {
    "_class": "MSImmutableFreeformGroupLayout",
    "do_objectID": "2542CEC7-9190-483F-9114-262FDA43B3B5"
  },
  "hasClickThrough": false,
  "hasClippingMask": false,
  "isFixedToViewport": false,
  "isFlippedHorizontal": false,
  "isFlippedVertical": false,
  "isLocked": false,
  "isVisible": true,
  "layerListExpandedType": 2,
  "layers": [
    {
      "class": "rectangle",
      "id": "8C8D8FEF-3F3B-4CDD-95FA-39ED1E5E15A8"
    },
    {
      "class": "bitmap",
      "id": "31AB6134-A1EA-4011-BFC9-559014D188F4"
    }
  ],
  "name": "7082530700_1_1_16 (1) copy 3",
  "nameIsFixed": false,
  "resizingConstraint": 63,
  "resizingType": 0,
  "rotation": 0,
  "shouldBreakMaskChain": false,
  "style": {
    "_class": "style",
    "do_objectID": "F904BAE5-8D04-45E2-8AA3-159CFF06A967",
    "endMarkerType": 0,
    "miterLimit": 10,
    "startMarkerType": 0,
    "windingRule": 1
  }
}