{
  "_class": "symbolInstance",
  "booleanOperation": -1,
  "clippingMaskMode": 0,
  "do_objectID": "D2AB1D86-9890-444A-B68D-7CDCC95C8589",
  "exportOptions": {
    "_class": "exportOptions",
    "do_objectID": "6631BFE3-F309-434C-930B-E48E5FBC544E",
    "exportFormats": [
    ],
    "includedLayerIds": [
    ],
    "layerOptions": 0,
    "shouldTrim": false
  },
  "frame": {
    "_class": "rect",
    "constrainProportions": false,
    "do_objectID": "AF95342C-8BA9-4ED4-BEC8-7309F2055EF7",
    "height": 48,
    "width": 200,
    "x": 400,
    "y": 0
  },
  "hasClippingMask": false,
  "horizontalSpacing": 0,
  "isFixedToViewport": false,
  "isFlippedHorizontal": false,
  "isFlippedVertical": false,
  "isLocked": false,
  "isVisible": true,
  "layerListExpandedType": 0,
  "name": "column 3",
  "nameIsFixed": true,
  "overrideValues": [
  ],
  "resizingConstraint": 63,
  "resizingType": 0,
  "rotation": 0,
  "scale": 1,
  "shouldBreakMaskChain": false,
  "style": {
    "_class": "style",
    "do_objectID": "8E9E27FF-A6F6-40E3-B45E-FD7A34C5DB4E",
    "endMarkerType": 0,
    "miterLimit": 10,
    "startMarkerType": 0,
    "windingRule": 1
  },
  "symbolID": "4FE2812D-387B-48D5-89C8-C33A6215F8E7",
  "verticalSpacing": 0
}