{
  "_class": "group",
  "booleanOperation": -1,
  "clippingMaskMode": 0,
  "do_objectID": "88B8516B-FF08-4CCB-A84C-3144DD8043BB",
  "exportOptions": {
    "_class": "exportOptions",
    "do_objectID": "0CEC2EAC-02C7-4B84-B597-01393617656E",
    "exportFormats": [
    ],
    "includedLayerIds": [
    ],
    "layerOptions": 0,
    "shouldTrim": false
  },
  "frame": {
    "_class": "rect",
    "constrainProportions": false,
    "do_objectID": "ABC35AC0-4D46-4BFD-9B61-41910176D932",
    "height": 14,
    "width": 225,
    "x": 160,
    "y": 288
  },
  "groupLayout": {
    "_class": "MSImmutableFreeformGroupLayout",
    "do_objectID": "B2FAE27F-D545-41C1-8647-D09014314E6F"
  },
  "hasClickThrough": false,
  "hasClippingMask": false,
  "isFixedToViewport": false,
  "isFlippedHorizontal": false,
  "isFlippedVertical": false,
  "isLocked": false,
  "isVisible": true,
  "layerListExpandedType": 0,
  "layers": [
    {
      "class": "text",
      "id": "852D3C1E-2C12-4A08-A437-4BD62490D50D"
    },
    {
      "class": "symbolInstance",
      "id": "2420631F-2BBF-480C-9EA5-2665A75BE9B3"
    }
  ],
  "name": "Group 3",
  "nameIsFixed": false,
  "resizingConstraint": 63,
  "resizingType": 0,
  "rotation": 0,
  "shouldBreakMaskChain": false,
  "style": {
    "_class": "style",
    "do_objectID": "D078C05B-1FF0-4797-BA7B-5590D95B2044",
    "endMarkerType": 0,
    "miterLimit": 10,
    "startMarkerType": 0,
    "windingRule": 1
  }
}