{
  "_class": "group",
  "booleanOperation": 0,
  "clippingMaskMode": 0,
  "do_objectID": "45741F53-CDA7-42F6-A31C-1B8ABAA8A247",
  "exportOptions": {
    "_class": "exportOptions",
    "do_objectID": "46BCD183-76EA-409B-AC37-7F5A20741687",
    "exportFormats": [
    ],
    "includedLayerIds": [
    ],
    "layerOptions": 0,
    "shouldTrim": false
  },
  "frame": {
    "_class": "rect",
    "constrainProportions": false,
    "do_objectID": "22B852F5-390C-4CD8-895A-B50FEDBB8953",
    "height": 21,
    "width": 208,
    "x": 16.88484848484847,
    "y": 114.7562326869806
  },
  "groupLayout": {
    "_class": "MSImmutableFreeformGroupLayout",
    "do_objectID": "65AD7904-8BD6-4A82-8DC9-706E93247C01"
  },
  "hasClickThrough": true,
  "hasClippingMask": false,
  "isFixedToViewport": false,
  "isFlippedHorizontal": false,
  "isFlippedVertical": false,
  "isLocked": false,
  "isVisible": true,
  "layerListExpandedType": 1,
  "layers": [
    {
      "class": "group",
      "id": "F4292B36-7522-42F8-9255-CC0B5D5CAA0E"
    },
    {
      "class": "text",
      "id": "4C7F1EB6-80D2-4535-8884-0FFA3129DCCA"
    },
    {
      "class": "text",
      "id": "CDD01DB4-FC10-4E20-8C31-CF8A9DA5D854"
    }
  ],
  "name": "2 star",
  "nameIsFixed": true,
  "resizingConstraint": 63,
  "resizingType": 0,
  "rotation": 0,
  "shouldBreakMaskChain": false,
  "style": {
    "_class": "style",
    "do_objectID": "95BDBF5D-4D59-4036-927F-DEF34AC73322",
    "endMarkerType": 0,
    "miterLimit": 10,
    "startMarkerType": 0,
    "windingRule": 1
  }
}