{
  "_class": "shapeGroup",
  "booleanOperation": -1,
  "clippingMaskMode": 0,
  "do_objectID": "29E90B71-93A7-4CC4-9D6A-195E3B5BDAF1",
  "exportOptions": {
    "_class": "exportOptions",
    "exportFormats": [
    ],
    "includedLayerIds": [
    ],
    "layerOptions": 0,
    "shouldTrim": false
  },
  "frame": {
    "_class": "rect",
    "constrainProportions": false,
    "height": 5.074007092198578,
    "width": 35.74412499999998,
    "x": 109.0233375,
    "y": 29.73091134751773
  },
  "groupLayout": {
    "_class": "MSImmutableFreeformGroupLayout"
  },
  "hasClickThrough": false,
  "hasClippingMask": false,
  "isFixedToViewport": false,
  "isFlippedHorizontal": false,
  "isFlippedVertical": false,
  "isLocked": false,
  "isVisible": true,
  "layerListExpandedType": 1,
  "layers": [
    {
      "class": "shapePath",
      "id": "009D3FCF-9952-4903-8492-A522B7844334"
    },
    {
      "class": "shapePath",
      "id": "71EAE734-A79D-40B2-ACFE-DC479ED56D03"
    },
    {
      "class": "shapePath",
      "id": "8EB1E42E-87AB-4CA7-BAB1-062E785E53AD"
    },
    {
      "class": "shapePath",
      "id": "EEA8EE5A-9C43-4B1D-A56C-908229DEA584"
    },
    {
      "class": "shapePath",
      "id": "E041B9B5-314E-4B18-82D4-EB841FFEFF9A"
    },
    {
      "class": "shapePath",
      "id": "67379312-F04A-4260-A6CF-5F4DEEAA119C"
    },
    {
      "class": "shapePath",
      "id": "535EA09A-F727-40BF-BA9B-83E00FC3682F"
    },
    {
      "class": "shapePath",
      "id": "D10D4529-2BA5-43E2-9916-3D69A903D57A"
    },
    {
      "class": "shapePath",
      "id": "A4E3F78A-A8D9-4E5A-B042-25C9D5293D7F"
    }
  ],
  "maintainScrollPosition": false,
  "name": "Fill 21",
  "nameIsFixed": false,
  "resizingConstraint": 63,
  "resizingType": 0,
  "rotation": 0,
  "shouldBreakMaskChain": false,
  "style": {
    "_class": "style",
    "blur": {
      "_class": "blur",
      "center": "{0.5, 0.5}",
      "isEnabled": false,
      "motionAngle": 0,
      "radius": 10,
      "saturation": 1,
      "type": 0
    },
    "borderOptions": {
      "_class": "borderOptions",
      "dashPattern": [
      ],
      "isEnabled": true,
      "lineCapStyle": 0,
      "lineJoinStyle": 0
    },
    "borders": [
    ],
    "colorControls": {
      "_class": "colorControls",
      "brightness": 0,
      "contrast": 1,
      "hue": 0,
      "isEnabled": false,
      "saturation": 1
    },
    "contextSettings": {
      "_class": "graphicsContextSettings",
      "blendMode": 0,
      "opacity": 1
    },
    "do_objectID": "B405F40E-9D82-4E0A-BBFB-5FB4F843BA6F",
    "endMarkerType": 0,
    "fills": [
      {
        "_class": "fill",
        "color": {
          "_class": "color",
          "alpha": 1,
          "blue": 0.1252310872077942,
          "green": 0.1220022812485695,
          "red": 0.1366096138954163
        },
        "contextSettings": {
          "_class": "graphicsContextSettings",
          "blendMode": 0,
          "opacity": 1
        },
        "fillType": 0,
        "gradient": {
          "_class": "gradient",
          "elipseLength": 0,
          "from": "{0.5, 0}",
          "gradientType": 0,
          "stops": [
            {
              "_class": "gradientStop",
              "color": {
                "_class": "color",
                "alpha": 1,
                "blue": 1,
                "green": 1,
                "red": 1
              },
              "position": 0
            },
            {
              "_class": "gradientStop",
              "color": {
                "_class": "color",
                "alpha": 1,
                "blue": 0,
                "green": 0,
                "red": 0
              },
              "position": 1
            }
          ],
          "to": "{0.5, 1}"
        },
        "isEnabled": true,
        "noiseIndex": 0,
        "noiseIntensity": 0,
        "patternFillType": 1,
        "patternTileScale": 1
      }
    ],
    "innerShadows": [
    ],
    "miterLimit": 10,
    "shadows": [
    ],
    "startMarkerType": 0,
    "windingRule": 1
  },
  "windingRule": 1
}