{
  "_class": "group",
  "booleanOperation": 0,
  "clippingMaskMode": 0,
  "do_objectID": "47D798B5-64AC-4E5E-8103-F6C4B9C8BCDE",
  "exportOptions": {
    "_class": "exportOptions",
    "do_objectID": "BC8BD516-2912-4255-8051-FCAA88D81581",
    "exportFormats": [
    ],
    "includedLayerIds": [
    ],
    "layerOptions": 0,
    "shouldTrim": false
  },
  "frame": {
    "_class": "rect",
    "constrainProportions": false,
    "do_objectID": "CFE81C67-59B2-4817-A3F2-F56CE89B511F",
    "height": 195,
    "width": 355,
    "x": 20,
    "y": 1919
  },
  "groupLayout": {
    "_class": "MSImmutableFreeformGroupLayout"
  },
  "hasClickThrough": false,
  "hasClippingMask": false,
  "isFixedToViewport": false,
  "isFlippedHorizontal": false,
  "isFlippedVertical": false,
  "isLocked": false,
  "isVisible": true,
  "layerListExpandedType": 0,
  "layers": [
    {
      "class": "text",
      "id": "B83C54A6-A37D-4078-A5D2-2BDAE9F83198"
    },
    {
      "class": "rectangle",
      "id": "EA3D73E6-4E80-4201-8CBF-B203E64201E2"
    },
    {
      "class": "text",
      "id": "C6ACF5AB-00FD-4329-A56A-E552FB31E280"
    },
    {
      "class": "text",
      "id": "9843B57E-D60F-4D71-8ECD-2F1B941AB580"
    },
    {
      "class": "text",
      "id": "D0B1834C-257A-4572-A8B5-A97AC312112C"
    },
    {
      "class": "bitmap",
      "id": "1273A656-C2CA-4D11-9D9C-E1281CF3C02D"
    },
    {
      "class": "rectangle",
      "id": "7A585D15-47D5-4BA5-BD0D-4F30619A4C3F"
    },
    {
      "class": "text",
      "id": "8651206D-ACD4-4ABC-86D4-99AEA2998582"
    },
    {
      "class": "text",
      "id": "CBC5D0BC-BB0B-42AE-A8D4-A91FED36071A"
    },
    {
      "class": "text",
      "id": "5EB02A28-8F67-4207-9B9F-EAB4128243ED"
    },
    {
      "class": "bitmap",
      "id": "FE86C593-B294-4259-AE68-7DC946AA754F"
    }
  ],
  "name": "Group 14",
  "nameIsFixed": false,
  "resizingConstraint": 63,
  "resizingType": 0,
  "rotation": 0,
  "shouldBreakMaskChain": false,
  "style": {
    "_class": "style",
    "do_objectID": "8A230407-7BF8-43D6-A2AD-661794DF8732",
    "endMarkerType": 0,
    "miterLimit": 10,
    "startMarkerType": 0,
    "windingRule": 1
  }
}