{
  "_class": "shapePath",
  "booleanOperation": -1,
  "clippingMaskMode": 0,
  "do_objectID": "44A61DE8-7DC9-4316-B4F5-63D89E502189",
  "edited": true,
  "exportOptions": {
    "_class": "exportOptions",
    "do_objectID": "2C6E8D85-BE60-403D-89C2-77F0E9BB90F7",
    "exportFormats": [
    ],
    "includedLayerIds": [
    ],
    "layerOptions": 0,
    "shouldTrim": false
  },
  "frame": {
    "_class": "rect",
    "constrainProportions": false,
    "do_objectID": "87C66C3A-BF51-4530-925E-570F9433B56F",
    "height": 0.1311352009108866,
    "width": 0.1059863482545609,
    "x": 18.01268020565353,
    "y": 23.44049888278933
  },
  "hasClippingMask": false,
  "isClosed": true,
  "isFixedToViewport": false,
  "isFlippedHorizontal": false,
  "isFlippedVertical": false,
  "isLocked": false,
  "isVisible": true,
  "layerListExpandedType": 0,
  "name": "Path",
  "nameIsFixed": false,
  "pointRadiusBehaviour": 0,
  "points": [
    {
      "_class": "curvePoint",
      "cornerRadius": 0,
      "curveFrom": "{0.074265234371169012, 0.085961657390234009}",
      "curveMode": 3,
      "curveTo": "{-0.09178584896889011, 0.35930735930736585}",
      "hasCurveFrom": true,
      "hasCurveTo": true,
      "point": "{0.011706454136086567, 0.18800247371674095}"
    },
    {
      "_class": "curvePoint",
      "cornerRadius": 0,
      "curveFrom": "{0.47664948748824776, 0.19418676561534803}",
      "curveMode": 4,
      "curveTo": "{0.43417130337799548, 0.094001236858405626}",
      "hasCurveFrom": true,
      "hasCurveTo": true,
      "point": "{0.51758301035812004, 0}"
    },
    {
      "_class": "curvePoint",
      "cornerRadius": 0,
      "curveFrom": "{0.92691823905686477, 0.91465677179964422}",
      "curveMode": 4,
      "curveTo": "{1.0929693223969239, 0.63883735312306955}",
      "hasCurveFrom": true,
      "hasCurveTo": true,
      "point": "{0.98793235805156732, 0.81076066790353762}"
    },
    {
      "_class": "curvePoint",
      "cornerRadius": 0,
      "curveFrom": "{0.52607864718016606, 0.80766852195425165}",
      "curveMode": 4,
      "curveTo": "{0.56855683129041834, 0.90228818800246524}",
      "hasCurveFrom": true,
      "hasCurveTo": true,
      "point": "{0.48514512431029383, 1}"
    }
  ],
  "resizingConstraint": 63,
  "resizingType": 0,
  "rotation": 0,
  "shouldBreakMaskChain": false,
  "style": {
    "_class": "style",
    "do_objectID": "52EC8766-B386-4B6F-8905-A6995E60EE61",
    "endMarkerType": 0,
    "fills": [
      {
        "_class": "fill",
        "color": {
          "_class": "color",
          "alpha": 1,
          "blue": 0.1764705882352941,
          "green": 0.1764705882352941,
          "red": 0.1764705882352941
        },
        "fillType": 0,
        "isEnabled": true,
        "noiseIndex": 0,
        "noiseIntensity": 0,
        "patternFillType": 1,
        "patternTileScale": 1
      }
    ],
    "miterLimit": 10,
    "startMarkerType": 0,
    "windingRule": 1
  }
}