{
  "_class": "shapePath",
  "booleanOperation": -1,
  "clippingMaskMode": 0,
  "do_objectID": "350C3FFB-595C-48C9-83A4-06C208267CDE",
  "edited": true,
  "exportOptions": {
    "_class": "exportOptions",
    "do_objectID": "620EACB6-A722-4CA6-A339-F30E71688181",
    "exportFormats": [
    ],
    "includedLayerIds": [
    ],
    "layerOptions": 0,
    "shouldTrim": false
  },
  "frame": {
    "_class": "rect",
    "constrainProportions": false,
    "do_objectID": "0AF5B528-EA41-411A-9985-88747FC7BD28",
    "height": 0.1058906030855589,
    "width": 0.1059863482545502,
    "x": 26.21180445913279,
    "y": 22.75509382518774
  },
  "hasClippingMask": false,
  "isClosed": true,
  "isFixedToViewport": false,
  "isFlippedHorizontal": false,
  "isFlippedVertical": false,
  "isLocked": false,
  "isVisible": true,
  "layerListExpandedType": 0,
  "name": "Path",
  "nameIsFixed": false,
  "pointRadiusBehaviour": 0,
  "points": [
    {
      "_class": "curvePoint",
      "cornerRadius": 0,
      "curveFrom": "{0.93984943082443806, 0.24758256855164973}",
      "curveMode": 4,
      "curveTo": "{0.36084943082443033, -0.10941743144837801}",
      "hasCurveFrom": true,
      "hasCurveTo": true,
      "point": "{0.56184943082445216, 0.016582568551655186}"
    },
    {
      "_class": "curvePoint",
      "cornerRadius": 0,
      "curveFrom": "{-0.25815056917554102, 0.51658256855165519}",
      "curveMode": 3,
      "curveTo": "{0.31884943082445716, 0.86758256855165428}",
      "hasCurveFrom": true,
      "hasCurveTo": true,
      "point": "{0.11984943082444488, 0.74758256855164973}"
    }
  ],
  "resizingConstraint": 63,
  "resizingType": 0,
  "rotation": 0,
  "shouldBreakMaskChain": false,
  "style": {
    "_class": "style",
    "do_objectID": "CC8FC278-AF39-42ED-9453-C250C9E78A5D",
    "endMarkerType": 0,
    "fills": [
      {
        "_class": "fill",
        "color": {
          "_class": "color",
          "alpha": 1,
          "blue": 0.1764705882352941,
          "green": 0.1764705882352941,
          "red": 0.1764705882352941
        },
        "fillType": 0,
        "isEnabled": true,
        "noiseIndex": 0,
        "noiseIntensity": 0,
        "patternFillType": 1,
        "patternTileScale": 1
      }
    ],
    "miterLimit": 10,
    "startMarkerType": 0,
    "windingRule": 1
  }
}